setup.py
model1/__init__.py
model1/base_action.py
model1/test.py
model1/validators.json
model1.egg-info/PKG-INFO
model1.egg-info/SOURCES.txt
model1.egg-info/dependency_links.txt
model1.egg-info/requires.txt
model1.egg-info/top_level.txt
model1/goods/__init__.py
model1/goods/action.py
model1/goods/main.py
model1/goods/model.py
model1/order/__init__.py
model1/order/action.py
model1/order/main.py
model1/order/model.py