Metadata-Version: 1.0
Name: model1
Version: 1.0.4.8
Summary: model1 sdk
Home-page: UNKNOWN
Author: skyeye
Author-email: skyeye@gmail.com
License: MIT Licence
Keywords: model1,xxx
Platform: any
